sigfig/__init__.py
sigfig/sigfig.py
sigfig-1.3.18.dist-info/LICENSE
sigfig-1.3.18.dist-info/METADATA
sigfig-1.3.18.dist-info/WHEEL
sigfig-1.3.18.dist-info/RECORD
